PytorchZhongwenWendang/README.md
PytorchZhongwenWendang/__init__.py
PytorchZhongwenWendang/__main__.py
PytorchZhongwenWendang/file.epub
PytorchZhongwenWendang/index.html
PytorchZhongwenWendang/css/__init__.py
PytorchZhongwenWendang/css/annotations.css
PytorchZhongwenWendang/css/main.css
PytorchZhongwenWendang/css/normalize.css
PytorchZhongwenWendang/css/popup.css
PytorchZhongwenWendang/font/__init__.py
PytorchZhongwenWendang/font/fontello.eot
PytorchZhongwenWendang/font/fontello.svg
PytorchZhongwenWendang/font/fontello.ttf
PytorchZhongwenWendang/font/fontello.woff
PytorchZhongwenWendang/img/__init__.py
PytorchZhongwenWendang/img/annotator-glyph-sprite.png
PytorchZhongwenWendang/img/annotator-icon-sprite.png
PytorchZhongwenWendang/img/apple-touch-icon.png
PytorchZhongwenWendang/img/cancelfullscreen.png
PytorchZhongwenWendang/img/close.png
PytorchZhongwenWendang/img/fullscreen.png
PytorchZhongwenWendang/img/loader.gif
PytorchZhongwenWendang/img/menu-icon.png
PytorchZhongwenWendang/img/save.png
PytorchZhongwenWendang/img/saved.png
PytorchZhongwenWendang/img/settings-s.png
PytorchZhongwenWendang/img/settings.png
PytorchZhongwenWendang/img/star.png
PytorchZhongwenWendang/js/__init__.py
PytorchZhongwenWendang/js/epub.js
PytorchZhongwenWendang/js/epub.min.js
PytorchZhongwenWendang/js/epub.min.map
PytorchZhongwenWendang/js/hooks.min.js
PytorchZhongwenWendang/js/hooks.min.map
PytorchZhongwenWendang/js/reader.js
PytorchZhongwenWendang/js/reader.js.map
PytorchZhongwenWendang/js/reader.min.js
PytorchZhongwenWendang/js/reader.min.map
PytorchZhongwenWendang/js/hooks/__init__.py
PytorchZhongwenWendang/js/hooks/extensions/__init__.py
PytorchZhongwenWendang/js/hooks/extensions/highlight.js
PytorchZhongwenWendang/js/libs/__init__.py
PytorchZhongwenWendang/js/libs/jquery.min.js
PytorchZhongwenWendang/js/libs/localforage.min.js
PytorchZhongwenWendang/js/libs/screenfull.js
PytorchZhongwenWendang/js/libs/screenfull.min.js
PytorchZhongwenWendang/js/libs/zip.min.js
pytorch_zhongwen_wendang-2024.3.2.0.dist-info/METADATA
pytorch_zhongwen_wendang-2024.3.2.0.dist-info/WHEEL
pytorch_zhongwen_wendang-2024.3.2.0.dist-info/entry_points.txt
pytorch_zhongwen_wendang-2024.3.2.0.dist-info/top_level.txt
pytorch_zhongwen_wendang-2024.3.2.0.dist-info/RECORD
